adam_lr_decay/__init__.py
adam_lr_decay/adam_lr_decay.py
adam_lr_decay-0.0.8.dist-info/LICENSE
adam_lr_decay-0.0.8.dist-info/METADATA
adam_lr_decay-0.0.8.dist-info/WHEEL
adam_lr_decay-0.0.8.dist-info/RECORD
