Metadata-Version: 2.1
Name: adam-lr-decay
Version: 0.0.8
Summary: Adam Layer-wise LR Decay
Home-page: https://github.com/OrigamiDream/adam-lr-decay
License: MIT
Keywords: machine-learning,deep-learning,tensorflow,optimizers
Author: OrigamiDream
Author-email: hello@origamidream.me
Requires-Python: >=3.8,<3.11
Classifier: Development Status :: 4 - Beta
Classifier: Intended Audience :: Developers
Classifier: License :: OSI Approved :: MIT License
Classifier: Programming Language :: Python :: 3
Classifier: Programming Language :: Python :: 3.8
Classifier: Programming Language :: Python :: 3.9
Classifier: Programming Language :: Python :: 3.10
Classifier: Topic :: Scientific/Engineering :: Artificial Intelligence
Provides-Extra: cpu
Provides-Extra: gpu
Provides-Extra: mac
Requires-Dist: flowchain (>=0.0.4,<0.0.5)
Requires-Dist: packaging
Requires-Dist: tensorflow (>=2.11,<2.12) ; extra == "gpu"
Requires-Dist: tensorflow-cpu (>=2.11,<2.12) ; extra == "cpu"
Requires-Dist: tensorflow-macos (==2.11.0) ; extra == "mac"
Requires-Dist: tensorflow-metal (==0.7.0) ; extra == "mac"
Project-URL: Repository, https://github.com/OrigamiDream/adam-lr-decay
